in_layers/__init__.py
in_layers/data/__init__.py
in_layers/data/backends/__init__.py
in_layers/data/backends/dynamodb/__init__.py
in_layers/data/backends/dynamodb/libs.py
in_layers/data/backends/dynamodb/services.py
in_layers/data/backends/mongodb/__init__.py
in_layers/data/backends/mongodb/libs.py
in_layers/data/backends/mongodb/services.py
in_layers/data/protocols.py
in_layers/data/services.py
in_layers_data-0.4.21.dist-info/METADATA
in_layers_data-0.4.21.dist-info/WHEEL
in_layers_data-0.4.21.dist-info/RECORD
