Metadata-Version: 2.4
Name: in-layers-data
Version: 0.4.21
Summary: A data layer for In Layers Core. (in-layers-core). Part of the Node in Layers ecosystem
License: GPLv3
Keywords: layers,python,in-layers,node,domains,data,models,orm
Author: Mike Cornwell
Author-email: mike@mikecornwell.com
Requires-Python: >=3.13,<4.0
Classifier: License :: Other/Proprietary License
Classifier: Programming Language :: Python :: 3
Classifier: Programming Language :: Python :: 3.13
Classifier: Programming Language :: Python :: 3.14
Requires-Dist: httpx (>=0.28.1,<0.29.0)
Requires-Dist: in-layers-core (>=0.4.2,<0.5.0)
Requires-Dist: pydantic (>=2.12.5,<3.0.0)
Requires-Dist: python-box (>=7,<9)
